{"atletas":[{"scout":{"FC":1,"PI":5},"atleta_id":87342,"rodada_id":27,"clube_id":284,"posicao_id":3,"status_id":7,"pontos_num":-1,"preco_num":6.84,"variacao_num":0.21,"media_num":2.03,"jogos_num":12,"slug":"","apelido":"Kannemann","apelido_abreviado":"Kannemann","nome":"Walter Kannemann","foto":"https:\/\/s.glbimg.com\/es\/sde\/f\/2021\/04\/29\/aab069ddcc3f87f133a2d6ea07c4edd4_FORMATO.png"},{"scout":{"FC":1,"PI":2},"atleta_id":51548,"rodada_id":27,"clube_id":264,"posicao_id":4,"status_id":7,"pontos_num":-0.7,"preco_num":8.82,"variacao_num":-0.43,"media_num":3.56,"jogos_num":12,"slug":"","apelido":"Giuliano","apelido_abreviado":"Giuliano","nome":"Giuliano Victor de Paula","foto":"https:\/\/s.glbimg.com\/es\/sde\/f\/2021\/07\/22\/1e8808fa091e5d4062730e04ed46b383_FORMATO.png"},{"scout":{"DS":3,"FS":1,"PI":4,"SG":1},"atleta_id":78478,"rodada_id":27,"clube_id":262,"posicao_id":3,"status_id":6,"pontos_num":8.1,"preco_num":11.74,"variacao_num":1.03,"media_num":3.91,"jogos_num":23,"slug":"","apelido":"Willian Ar\u00e3o","apelido_abreviado":"W. Ar\u00e3o","nome":"Willian Souza Ar\u00e3o da Silva","foto":"https:\/\/s.glbimg.com\/es\/sde\/f\/2021\/05\/01\/5696091eeba19b79c51d753792490f14_FORMATO.png"},{"scout":{"DS":1,"FC":1,"FD":1,"FF":1,"FS":2,"PI":5},"atleta_id":61188,"rodada_id":27,"clube_id":265,"posicao_id":5,"status_id":7,"pontos_num":3,"preco_num":13.58,"variacao_num":0.41,"media_num":4.31,"jogos_num":24,"slug":"","apelido":"Gilberto","apelido_abreviado":"Gilberto","nome":"Gilberto Oliveira Souza J\u00fanior","foto":"https:\/\/s.glbimg.com\/es\/sde\/f\/2021\/04\/19\/084597dfc92b63b3485d5ed7b75cdfa6_FORMATO.png"},{"scout":{"CA":1,"DS":1,"FC":1,"FF":1,"FS":1,"I":1,"PI":9},"atleta_id":81677,"rodada_id":27,"clube_id":277,"posicao_id":4,"status_id":7,"pontos_num":-1.6,"preco_num":6.97,"variacao_num":-0.3,"media_num":2.23,"jogos_num":18,"slug":"","apelido":"Carlos S\u00e1nchez","apelido_abreviado":"C. S\u00e1nchez","nome":"Carlos Andr\u00e9s S\u00e1nchez Arcosa","foto":"https:\/\/s.glbimg.com\/es\/sde\/f\/2021\/05\/04\/0114554943a088276966824a3ae8496b_FORMATO.png"},{"scout":{"DS":4,"FC":4,"PI":10,"SG":1},"atleta_id":97899,"rodada_id":27,"clube_id":265,"posicao_id":2,"status_id":7,"pontos_num":6,"preco_num":11.33,"variacao_num":-0.38,"media_num":4.61,"jogos_num":19,"slug":"","apelido":"Matheus Bahia","apelido_abreviado":"M. Bahia","nome":"Matheus Bahia Santos","foto":"https:\/\/s.glbimg.com\/es\/sde\/f\/2021\/04\/19\/52f1b5df1a1d88d986e939213804c1d0_FORMATO.png"},{"scout":{"DS":2,"FC":1,"PI":4},"atleta_id":99440,"rodada_id":27,"clube_id":373,"posicao_id":4,"status_id":6,"pontos_num":1.1,"preco_num":4.71,"variacao_num":-0.12,"media_num":3.1,"jogos_num":23,"slug":"","apelido":"Baralhas","apelido_abreviado":"Baralhas","nome":"Gabriel Baralhas dos Santos","foto":"https:\/\/s.glbimg.com\/es\/sde\/f\/2020\/10\/20\/d1b6cda28d3190a8ba17446d082ac2ab_FORMATO.png"},{"scout":{"FC":1,"I":2,"PI":5},"atleta_id":72389,"rodada_id":27,"clube_id":315,"posicao_id":5,"status_id":7,"pontos_num":-2,"preco_num":2.67,"variacao_num":-0.93,"media_num":3.22,"jogos_num":20,"slug":"","apelido":"Mike","apelido_abreviado":"Mike","nome":"Mike dos Santos Nenatarvicius","foto":"https:\/\/s.glbimg.com\/es\/sde\/f\/2021\/03\/23\/37b715a26faf266068223fd157a93d83_FORMATO.png"},{"scout":{"FC":1,"FS":4,"I":1,"PI":6},"atleta_id":68952,"rodada_id":27,"clube_id":277,"posicao_id":5,"status_id":7,"pontos_num":0.4,"preco_num":16.3,"variacao_num":-0.47,"media_num":4.98,"jogos_num":18,"slug":"","apelido":"Marinho","apelido_abreviado":"Marinho","nome":"M\u00e1rio S\u00e9rgio Santos Costa","foto":"https:\/\/s.glbimg.com\/es\/sde\/f\/2021\/05\/04\/ed157c234599d01c370049565c5fa3a8_FORMATO.png"},{"scout":{},"atleta_id":41929,"rodada_id":27,"clube_id":262,"posicao_id":6,"status_id":7,"pontos_num":5.31,"preco_num":15,"variacao_num":-0.11,"media_num":5.44,"jogos_num":15,"slug":"","apelido":"Renato Ga\u00facho","apelido_abreviado":"R. Ga\u00facho","nome":"Renato Portaluppi","foto":"https:\/\/s.glbimg.com\/es\/sde\/f\/2021\/07\/12\/a1f0a8f108ede4bf4ca2033148bcb547_FORMATO.png"},{"scout":{"DS":3,"FS":2,"PI":5},"atleta_id":107750,"rodada_id":27,"clube_id":284,"posicao_id":2,"status_id":7,"pontos_num":3.5,"preco_num":10.18,"variacao_num":0.23,"media_num":4.56,"jogos_num":20,"slug":"","apelido":"Vanderson","apelido_abreviado":"Vanderson","nome":"Vanderson de Oliveira Campos","foto":"https:\/\/s.glbimg.com\/es\/sde\/f\/2021\/04\/29\/7e1be4b535a30128fdd5980f0137732a_FORMATO.png"},{"scout":{"DE":4,"SG":1},"atleta_id":86508,"rodada_id":27,"clube_id":277,"posicao_id":1,"status_id":6,"pontos_num":9,"preco_num":5.03,"variacao_num":1.03,"media_num":9,"jogos_num":1,"slug":"","apelido":"Jandrei","apelido_abreviado":"Jandrei","nome":"Jandrei Chitolina Carniel","foto":"https:\/\/s.glbimg.com\/es\/sde\/f\/2021\/08\/31\/b98c287801bcb3150a4be5dbb4b95ceb_FORMATO.png"}],"reservas":[{"scout":{},"atleta_id":38877,"rodada_id":27,"clube_id":282,"posicao_id":2,"status_id":6,"pontos_num":0,"preco_num":6.93,"variacao_num":0,"media_num":3.83,"jogos_num":15,"slug":"","apelido":"Mariano","apelido_abreviado":"Mariano","nome":"Mariano Ferreira Filho","foto":"https:\/\/s.glbimg.com\/es\/sde\/f\/2021\/05\/02\/cefb911612e5a3e04586a326c9c8647b_FORMATO.png"},{"scout":{"FC":2,"FS":1,"I":1,"PI":7},"atleta_id":114648,"rodada_id":27,"clube_id":265,"posicao_id":5,"status_id":7,"pontos_num":-1.7,"preco_num":3.1,"variacao_num":-0.49,"media_num":2.57,"jogos_num":3,"slug":"","apelido":"Ra\u00ed Nascimento","apelido_abreviado":"R. Nascimento","nome":"Ra\u00ed Nascimento de Oliveira","foto":"https:\/\/s.glbimg.com\/es\/sde\/f\/2021\/09\/23\/4cf54964ec0d9d30f88c8400a4a7325b_FORMATO.png"},{"scout":{"DE":5,"SG":1},"atleta_id":69051,"rodada_id":27,"clube_id":265,"posicao_id":1,"status_id":7,"pontos_num":10,"preco_num":3.39,"variacao_num":0.54,"media_num":6.75,"jogos_num":4,"slug":"","apelido":"Danilo Fernandes","apelido_abreviado":"D. Fernandes","nome":"Danilo Fernandes Batista","foto":"https:\/\/s.glbimg.com\/es\/sde\/f\/2021\/07\/09\/20fc957ba7814a77a6504973b2c7849f_FORMATO.png"},{"scout":{"DS":4,"FC":1,"FF":1,"PI":5,"SG":1},"atleta_id":90012,"rodada_id":27,"clube_id":277,"posicao_id":3,"status_id":7,"pontos_num":8.8,"preco_num":7.16,"variacao_num":1.45,"media_num":3.77,"jogos_num":6,"slug":"","apelido":"Vel\u00e1zquez","apelido_abreviado":"Vel\u00e1zquez","nome":"Emiliano Daniel Vel\u00e1zquez Maldonado","foto":"https:\/\/s.glbimg.com\/es\/sde\/f\/2021\/08\/31\/b68632e2dd6a5264c1812daca5732395_FORMATO.png"},{"scout":{"DS":1,"FS":2,"PI":6},"atleta_id":109588,"rodada_id":27,"clube_id":264,"posicao_id":4,"status_id":7,"pontos_num":1.4,"preco_num":3.16,"variacao_num":-0.83,"media_num":2.84,"jogos_num":9,"slug":"","apelido":"Gabriel Pereira","apelido_abreviado":"G. Pereira","nome":"Gabriel Pereira dos Santos","foto":"https:\/\/s.glbimg.com\/es\/sde\/f\/2021\/08\/06\/ce3b05d4b17909aee62a997d20bc7edc_FORMATO.png"}],"time":{"temporada_inicial":2020,"cor_fundo_escudo":"ff241d","cor_camisa":"ffffff","cor_borda_escudo":"cccccc","foto_perfil":"https:\/\/s3.glbimg.com\/v1\/AUTH_58d78b787ec34892b5aaa0c7a146155f\/placeholder\/perfil.png","nome_cartola":"Felipe Lauria","globo_id":"09e19082-a473-47be-ab45-7ac769872968","nome":"Santa Carupita S.C.","url_escudo_svg":"https:\/\/s3.glbimg.com\/v1\/AUTH_58d78b787ec34892b5aaa0c7a146155f\/cartola_svg_179\/escudo\/68\/27\/22\/0009e19082-a473-47be-ab45-7ac76987296820200912082722","url_escudo_png":"https:\/\/s2.glbimg.com\/IwAhtikiMl7hdJnEuqBipwx_6nU=\/https:\/\/s3.glbimg.com\/v1\/AUTH_58d78b787ec34892b5aaa0c7a146155f\/cartola_svg_179\/escudo\/68\/27\/22\/0009e19082-a473-47be-ab45-7ac76987296820200912082722","url_camisa_svg":"https:\/\/s3.glbimg.com\/v1\/AUTH_58d78b787ec34892b5aaa0c7a146155f\/cartola_svg_197\/camisa\/68\/07\/04\/0009e19082-a473-47be-ab45-7ac76987296820210905160704","url_camisa_png":"https:\/\/s2.glbimg.com\/E66yRzQgWzUqGUAuvHDK8eB6BnE=\/https:\/\/s3.glbimg.com\/v1\/AUTH_58d78b787ec34892b5aaa0c7a146155f\/cartola_svg_197\/camisa\/68\/07\/04\/0009e19082-a473-47be-ab45-7ac76987296820210905160704","slug":"santa-carupita-s-c","cor_secundaria_estampa_escudo":"000000","sorteio_pro_num":null,"cor_primaria_estampa_camisa":"ffffff","cor_secundaria_estampa_camisa":"000000","cor_primaria_estampa_escudo":"fce37e","rodada_time_id":38,"facebook_id":null,"tipo_escudo":2,"time_id":25906150,"tipo_adorno":4,"esquema_id":1,"tipo_estampa_camisa":6,"tipo_estampa_escudo":1,"patrocinador1_id":67,"clube_id":266,"tipo_camisa":1,"patrocinador2_id":68,"assinante":false,"simplificado":false,"cadastro_completo":true,"lgpd_removido":false,"lgpd_quarentena":false},"pontos_campeonato":1497.0078125,"capitao_id":68952,"pontos":31.510009765625,"esquema_id":3,"rodada_atual":27,"patrimonio":187.22,"valor_time":0,"ranking":{"atual":{"ranking_id":6,"mes":12,"posicao":376240},"anterior":{"ranking_id":9,"mes":11,"posicao":162878},"melhor_ranking_id":9}}