[{"time":"Tima\u00e7o do Mumu","pontos":124.16,"rodada":32},{"time":"MIRANDEXTER F.R","pontos":120,"rodada":30},{"time":"TimeThunder","pontos":114.32,"rodada":6},{"time":"FLAPOLINARIO","pontos":111.38,"rodada":32},{"time":"MIRANDEXTER F.R","pontos":110.47,"rodada":25},{"time":"MIRANDEXTER F.R","pontos":109.22,"rodada":10},{"time":"FLAPOLINARIO","pontos":108.48,"rodada":13},{"time":"Tima\u00e7o do Mumu","pontos":107.68,"rodada":6},{"time":"ROSSINENSE","pontos":105.95,"rodada":12},{"time":"TimeThunder","pontos":105.3,"rodada":8}]